[
    {
        "pk": 1, 
        "model": "auth.user", 
        "fields": {
            "username": "jfurrer", 
            "first_name": "Julien", 
            "last_name": "Furrer", 
            "is_active": true, 
            "is_superuser": true, 
            "is_staff": true, 
            "last_login": "2010-04-16 15:16:11", 
            "groups": [
                5
            ], 
            "user_permissions": [], 
            "password": "sha1$548f8$885d91557830af4885bb1a5db124f14197591587", 
            "email": "julien.furrer@unil.ch", 
            "date_joined": "2009-06-24 16:33:39"
        }
    }, 
    {
        "pk": 2, 
        "model": "auth.user", 
        "fields": {
            "username": "toto", 
            "first_name": "", 
            "last_name": "", 
            "is_active": true, 
            "is_superuser": false, 
            "is_staff": true, 
            "last_login": "2009-07-24 08:50:34", 
            "groups": [
                3
            ], 
            "user_permissions": [], 
            "password": "sha1$39dc6$ea9874afa5e1f4782caff72506b741a92c3ea99d", 
            "email": "", 
            "date_joined": "2009-07-24 08:44:36"
        }
    },
    {
        "pk": 6, 
        "model": "fiches.society", 
        "fields": {
            "name": "Soci\u00e9t\u00e9 \u00e9conomique - Berne"
        }
    }, 
    {
        "pk": 5, 
        "model": "fiches.society", 
        "fields": {
            "name": "Soci\u00e9t\u00e9 morale - Lausanne"
        }
    }, 
    {
        "pk": 7, 
        "model": "fiches.society", 
        "fields": {
            "name": "Soci\u00e9t\u00e9 \u00e9conomique - Yverdon"
        }
    }, 
    {
        "pk": 8, 
        "model": "fiches.society", 
        "fields": {
            "name": "Soci\u00e9t\u00e9 \u00e9conomique - Vevey"
        }
    }, 
    {
        "pk": 9, 
        "model": "fiches.society", 
        "fields": {
            "name": "Soci\u00e9t\u00e9 des citoyens (Patriotische Gesellschaft) - Berne"
        }
    }, 
    {
        "pk": 10, 
        "model": "fiches.society", 
        "fields": {
            "name": "Acad\u00e9mie de Lausanne"
        }
    }, 
    {
        "pk": 11, 
        "model": "fiches.society", 
        "fields": {
            "name": "Soci\u00e9t\u00e9 des sciences physiques - Lausanne"
        }
    }, 
    {
        "pk": 12, 
        "model": "fiches.society", 
        "fields": {
            "name": "Soci\u00e9t\u00e9 \u00e9conomique - Lausanne"
        }
    }, 
    {
        "pk": 13, 
        "model": "fiches.society", 
        "fields": {
            "name": "Soci\u00e9t\u00e9 de Monsieur de Comte de Lippe - Lausanne"
        }
    }, 
    {
        "pk": 14, 
        "model": "fiches.society", 
        "fields": {
            "name": "Soci\u00e9t\u00e9 morale - Berne"
        }
    }, 
    {
        "pk": 15, 
        "model": "fiches.society", 
        "fields": {
            "name": "Soci\u00e9t\u00e9 litt\u00e9raire - Lausanne (1772-1782)"
        }
    }, 
    {
        "pk": 16, 
        "model": "fiches.society", 
        "fields": {
            "name": "Soci\u00e9t\u00e9 litt\u00e9raire - Morges"
        }
    }, 
    {
        "pk": 17, 
        "model": "fiches.society", 
        "fields": {
            "name": "Soci\u00e9t\u00e9 \u00e9conomique - Nyon"
        }
    }, 
    {
        "pk": 18, 
        "model": "fiches.society", 
        "fields": {
            "name": "Soci\u00e9t\u00e9 \u00e9conomique - Payerne"
        }
    }, 
    {
        "pk": 19, 
        "model": "fiches.society", 
        "fields": {
            "name": "Soci\u00e9t\u00e9 helv\u00e9tique"
        }
    }, 
    {
        "pk": 20, 
        "model": "fiches.society", 
        "fields": {
            "name": "Groupe de Coppet"
        }
    }, 
    {
        "pk": 21, 
        "model": "fiches.society", 
        "fields": {
            "name": "Soci\u00e9t\u00e9 morale - Zurich"
        }
    }, 
    {
        "pk": 22, 
        "model": "fiches.society", 
        "fields": {
            "name": "Club helv\u00e9tique de Paris"
        }
    }, 
    {
        "pk": 23, 
        "model": "fiches.society", 
        "fields": {
            "name": "Acad\u00e9mie des sciences de Paris"
        }
    }, 
    {
        "pk": 24, 
        "model": "fiches.society", 
        "fields": {
            "name": "Cercle de la Rue de Bourg - Lausanne (1761-1803)"
        }
    }, 
    {
        "pk": 25, 
        "model": "fiches.society", 
        "fields": {
            "name": "Acad\u00e9mie Royale de G\u00f6ttingen"
        }
    }, 
    {
        "pk": 26, 
        "model": "fiches.society", 
        "fields": {
            "name": "Soci\u00e9t\u00e9 Royale de Londres"
        }
    }, 
    {
        "pk": 27, 
        "model": "fiches.society", 
        "fields": {
            "name": "Acad\u00e9mie de Stockholm"
        }
    }, 
    {
        "pk": 28, 
        "model": "fiches.society", 
        "fields": {
            "name": "Acad\u00e9mie de Groningen"
        }
    }, 
    {
        "pk": 29, 
        "model": "fiches.society", 
        "fields": {
            "name": "Acad\u00e9mie de St. Petersbourg"
        }
    }, 
    {
        "pk": 30, 
        "model": "fiches.society", 
        "fields": {
            "name": "Politisches Institut (Berne)"
        }
    }, 
    {
        "pk": 31, 
        "model": "fiches.society", 
        "fields": {
            "name": "Soci\u00e9t\u00e9 litt\u00e9raire"
        }
    }, 
    {
        "pk": 32, 
        "model": "fiches.society", 
        "fields": {
            "name": "Soci\u00e9t\u00e9 morale"
        }
    }, 
    {
        "pk": 33, 
        "model": "fiches.society", 
        "fields": {
            "name": "Soci\u00e9t\u00e9 \u00e9conomique"
        }
    }, 
    {
        "pk": 36, 
        "model": "fiches.society", 
        "fields": {
            "name": "Acad\u00e9mie Royale des sciences de Berlin"
        }
    }, 
    {
        "pk": 37, 
        "model": "fiches.society", 
        "fields": {
            "name": "Acad\u00e9mie de Dijon"
        }
    }, 
    {
        "pk": 38, 
        "model": "fiches.society", 
        "fields": {
            "name": "Acad\u00e9mie de Besan\u00e7on"
        }
    }, 
    {
        "pk": 27, 
        "model": "fiches.primarykeyword", 
        "fields": {
            "word": "Arts et litt\u00e9rature"
        }
    },
    {
        "pk": 6, 
        "model": "fiches.primarykeyword", 
        "fields": {
            "word": "Droit et justice"
        }
    }, 
    {
        "pk": 180, 
        "model": "fiches.primarykeyword", 
        "fields": {
            "word": "Economie"
        }
    }, 
    {
        "pk": 11, 
        "model": "fiches.primarykeyword", 
        "fields": {
            "word": "Histoire"
        }
    }, 
    {
        "pk": 181, 
        "model": "fiches.primarykeyword", 
        "fields": {
            "word": "Lieu et g\u00e9ographie"
        }
    }, 
    {
        "pk": 7, 
        "model": "fiches.primarykeyword", 
        "fields": {
            "word": "Philosophie"
        }
    }, 
    {
        "pk": 14, 
        "model": "fiches.primarykeyword", 
        "fields": {
            "word": "Politique"
        }
    }, 
    {
        "pk": 18, 
        "model": "fiches.primarykeyword", 
        "fields": {
            "word": "Religion"
        }
    }, 
    {
        "pk": 12, 
        "model": "fiches.primarykeyword", 
        "fields": {
            "word": "Sciences"
        }
    }, 
    {
        "pk": 19, 
        "model": "fiches.primarykeyword", 
        "fields": {
            "word": "Soci\u00e9t\u00e9"
        }
    }, 
    {
        "pk": 116, 
        "model": "fiches.secondarykeyword", 
        "fields": {
            "word": "G\u00e9ographie", 
            "parent": null
        }
    }, 
    {
        "pk": 5, 
        "model": "fiches.secondarykeyword", 
        "fields": {
            "word": "Architecture", 
            "parent": 27
        }
    }, 
    {
        "pk": 95, 
        "model": "fiches.secondarykeyword", 
        "fields": {
            "word": "Bibliographie", 
            "parent": 27
        }
    }, 
    {
        "pk": 121, 
        "model": "fiches.secondarykeyword", 
        "fields": {
            "word": "Biblioth\u00e8que", 
            "parent": 27
        }
    }, 
    {
        "pk": 92, 
        "model": "fiches.secondarykeyword", 
        "fields": {
            "word": "Biographie", 
            "parent": 27
        }
    }, 
    {
        "pk": 199, 
        "model": "fiches.secondarykeyword", 
        "fields": {
            "word": "Caricature", 
            "parent": 27
        }
    }, 
    {
        "pk": 207, 
        "model": "fiches.secondarykeyword", 
        "fields": {
            "word": "Compte rendu", 
            "parent": 27
        }
    }, 
    {
        "pk": 136, 
        "model": "fiches.secondarykeyword", 
        "fields": {
            "word": "Correspondance", 
            "parent": 27
        }
    }, 
    {
        "pk": 208, 
        "model": "fiches.secondarykeyword", 
        "fields": {
            "word": "Critique litt\u00e9raire", 
            "parent": 27
        }
    }, 
    {
        "pk": 174, 
        "model": "fiches.secondarykeyword", 
        "fields": {
            "word": "Danse", 
            "parent": 27
        }
    }, 
    {
        "pk": 209, 
        "model": "fiches.secondarykeyword", 
        "fields": {
            "word": "Ecrits personnels", 
            "parent": 27
        }
    }, 
    {
        "pk": 210, 
        "model": "fiches.secondarykeyword", 
        "fields": {
            "word": "Edition/imprimerie", 
            "parent": 27
        }
    }, 
    {
        "pk": 139, 
        "model": "fiches.secondarykeyword", 
        "fields": {
            "word": "Encyclop\u00e9die", 
            "parent": 27
        }
    }, 
    {
        "pk": 194, 
        "model": "fiches.secondarykeyword", 
        "fields": {
            "word": "Erudition", 
            "parent": 27
        }
    }, 
    {
        "pk": 128, 
        "model": "fiches.secondarykeyword", 
        "fields": {
            "word": "Fable", 
            "parent": 27
        }
    }, 
    {
        "pk": 138, 
        "model": "fiches.secondarykeyword", 
        "fields": {
            "word": "G\u00e9n\u00e9alogie", 
            "parent": 27
        }
    }, 
    {
        "pk": 203, 
        "model": "fiches.secondarykeyword", 
        "fields": {
            "word": "Grammaire", 
            "parent": 27
        }
    }, 
    {
        "pk": 211, 
        "model": "fiches.secondarykeyword", 
        "fields": {
            "word": "Helv\u00e9tisme", 
            "parent": 27
        }
    }, 
    {
        "pk": 212, 
        "model": "fiches.secondarykeyword", 
        "fields": {
            "word": "Idylle/pastorale", 
            "parent": 27
        }
    }, 
    {
        "pk": 213, 
        "model": "fiches.secondarykeyword", 
        "fields": {
            "word": "Jeux litt\u00e9raires", 
            "parent": 27
        }
    }, 
    {
        "pk": 214, 
        "model": "fiches.secondarykeyword", 
        "fields": {
            "word": "Journaux/presse p\u00e9riodique", 
            "parent": 27
        }
    }, 
    {
        "pk": 215, 
        "model": "fiches.secondarykeyword", 
        "fields": {
            "word": "Litt\u00e9rature nationale", 
            "parent": 27
        }
    }, 
    {
        "pk": 9, 
        "model": "fiches.secondarykeyword", 
        "fields": {
            "word": "Litt\u00e9rature/vie litt\u00e9raire", 
            "parent": 27
        }
    }, 
    {
        "pk": 149, 
        "model": "fiches.secondarykeyword", 
        "fields": {
            "word": "M\u00e9daille", 
            "parent": 27
        }
    }, 
    {
        "pk": 130, 
        "model": "fiches.secondarykeyword", 
        "fields": {
            "word": "Mercure suisse/Journal helv\u00e9tique", 
            "parent": 27
        }
    }, 
    {
        "pk": 182, 
        "model": "fiches.secondarykeyword", 
        "fields": {
            "word": "Musique et art lyrique", 
            "parent": 27
        }
    }, 
    {
        "pk": 154, 
        "model": "fiches.secondarykeyword", 
        "fields": {
            "word": "Oraison fun\u00e8bre", 
            "parent": 27
        }
    }, 
    {
        "pk": 120, 
        "model": "fiches.secondarykeyword", 
        "fields": {
            "word": "Ordonnance", 
            "parent": 27
        }
    }, 
    {
        "pk": 98, 
        "model": "fiches.secondarykeyword", 
        "fields": {
            "word": "Pamphlet", 
            "parent": 27
        }
    }, 
    {
        "pk": 152, 
        "model": "fiches.secondarykeyword", 
        "fields": {
            "word": "Peinture", 
            "parent": 27
        }
    }, 
    {
        "pk": 96, 
        "model": "fiches.secondarykeyword", 
        "fields": {
            "word": "Po\u00e9sie", 
            "parent": 27
        }
    }, 
    {
        "pk": 82, 
        "model": "fiches.secondarykeyword", 
        "fields": {
            "word": "Presse", 
            "parent": 27
        }
    }, 
    {
        "pk": 216, 
        "model": "fiches.secondarykeyword", 
        "fields": {
            "word": "R\u00e9cit de voyage", 
            "parent": 27
        }
    }, 
    {
        "pk": 206, 
        "model": "fiches.secondarykeyword", 
        "fields": {
            "word": "Rh\u00e9torique", 
            "parent": 27
        }
    }, 
    {
        "pk": 217, 
        "model": "fiches.secondarykeyword", 
        "fields": {
            "word": "Roman", 
            "parent": 27
        }
    }, 
    {
        "pk": 66, 
        "model": "fiches.secondarykeyword", 
        "fields": {
            "word": "Satire", 
            "parent": 27
        }
    }, 
    {
        "pk": 181, 
        "model": "fiches.secondarykeyword", 
        "fields": {
            "word": "Th\u00e9\u00e2tre", 
            "parent": 27
        }
    }, 
    {
        "pk": 200, 
        "model": "fiches.secondarykeyword", 
        "fields": {
            "word": "Droit coutumier", 
            "parent": 6
        }
    }, 
    {
        "pk": 110, 
        "model": "fiches.secondarykeyword", 
        "fields": {
            "word": "Droit des gens", 
            "parent": 6
        }
    }, 
    {
        "pk": 51, 
        "model": "fiches.secondarykeyword", 
        "fields": {
            "word": "Droit naturel", 
            "parent": 6
        }
    }, 
    {
        "pk": 107, 
        "model": "fiches.secondarykeyword", 
        "fields": {
            "word": "Droit p\u00e9nal", 
            "parent": 6
        }
    }, 
    {
        "pk": 165, 
        "model": "fiches.secondarykeyword", 
        "fields": {
            "word": "Droit publique", 
            "parent": 6
        }
    }, 
    {
        "pk": 53, 
        "model": "fiches.secondarykeyword", 
        "fields": {
            "word": "L\u00e9gislation", 
            "parent": 6
        }
    }, 
    {
        "pk": 151, 
        "model": "fiches.secondarykeyword", 
        "fields": {
            "word": "Propri\u00e9t\u00e9", 
            "parent": 6
        }
    }, 
    {
        "pk": 176, 
        "model": "fiches.secondarykeyword", 
        "fields": {
            "word": "Torture", 
            "parent": 6
        }
    }, 
    {
        "pk": 17, 
        "model": "fiches.secondarykeyword", 
        "fields": {
            "word": "Agriculture", 
            "parent": 180
        }
    }, 
    {
        "pk": 16, 
        "model": "fiches.secondarykeyword", 
        "fields": {
            "word": "Artisanat, industrie", 
            "parent": 180
        }
    }, 
    {
        "pk": 15, 
        "model": "fiches.secondarykeyword", 
        "fields": {
            "word": "Commerce", 
            "parent": 180
        }
    }, 
    {
        "pk": 41, 
        "model": "fiches.secondarykeyword", 
        "fields": {
            "word": "Dette publique", 
            "parent": 180
        }
    }, 
    {
        "pk": 141, 
        "model": "fiches.secondarykeyword", 
        "fields": {
            "word": "Economie domestique (Haushalt)", 
            "parent": 180
        }
    }, 
    {
        "pk": 45, 
        "model": "fiches.secondarykeyword", 
        "fields": {
            "word": "Economie politique", 
            "parent": 180
        }
    }, 
    {
        "pk": 34, 
        "model": "fiches.secondarykeyword", 
        "fields": {
            "word": "Finance", 
            "parent": 180
        }
    }, 
    {
        "pk": 23, 
        "model": "fiches.secondarykeyword", 
        "fields": {
            "word": "Luxe", 
            "parent": 180
        }
    }, 
    {
        "pk": 79, 
        "model": "fiches.secondarykeyword", 
        "fields": {
            "word": "Physiocratie", 
            "parent": 180
        }
    }, 
    {
        "pk": 218, 
        "model": "fiches.secondarykeyword", 
        "fields": {
            "word": "Antiquaires/\u00e9rudits", 
            "parent": 11
        }
    }, 
    {
        "pk": 52, 
        "model": "fiches.secondarykeyword", 
        "fields": {
            "word": "Antiquit\u00e9", 
            "parent": 11
        }
    }, 
    {
        "pk": 196, 
        "model": "fiches.secondarykeyword", 
        "fields": {
            "word": "Arch\u00e9ologie", 
            "parent": 11
        }
    }, 
    {
        "pk": 219, 
        "model": "fiches.secondarykeyword", 
        "fields": {
            "word": "Helv\u00e9tique", 
            "parent": 11
        }
    }, 
    {
        "pk": 220, 
        "model": "fiches.secondarykeyword", 
        "fields": {
            "word": "Histoire litt\u00e9raire", 
            "parent": 11
        }
    }, 
    {
        "pk": 97, 
        "model": "fiches.secondarykeyword", 
        "fields": {
            "word": "Historiographie", 
            "parent": 11
        }
    }, 
    {
        "pk": 197, 
        "model": "fiches.secondarykeyword", 
        "fields": {
            "word": "Numismatique", 
            "parent": 11
        }
    }, 
    {
        "pk": 24, 
        "model": "fiches.secondarykeyword", 
        "fields": {
            "word": "R\u00e9forme", 
            "parent": 11
        }
    }, 
    {
        "pk": 25, 
        "model": "fiches.secondarykeyword", 
        "fields": {
            "word": "Refuge", 
            "parent": 11
        }
    }, 
    {
        "pk": 81, 
        "model": "fiches.secondarykeyword", 
        "fields": {
            "word": "R\u00e9publique helv\u00e9tique", 
            "parent": 11
        }
    }, 
    {
        "pk": 44, 
        "model": "fiches.secondarykeyword", 
        "fields": {
            "word": "Restauration", 
            "parent": 11
        }
    }, 
    {
        "pk": 115, 
        "model": "fiches.secondarykeyword", 
        "fields": {
            "word": "Alpes", 
            "parent": 181
        }
    }, 
    {
        "pk": 89, 
        "model": "fiches.secondarykeyword", 
        "fields": {
            "word": "Am\u00e9rique", 
            "parent": 181
        }
    }, 
    {
        "pk": 68, 
        "model": "fiches.secondarykeyword", 
        "fields": {
            "word": "Angleterre", 
            "parent": 181
        }
    }, 
    {
        "pk": 122, 
        "model": "fiches.secondarykeyword", 
        "fields": {
            "word": "Asie", 
            "parent": 181
        }
    }, 
    {
        "pk": 86, 
        "model": "fiches.secondarykeyword", 
        "fields": {
            "word": "Autriche", 
            "parent": 181
        }
    }, 
    {
        "pk": 80, 
        "model": "fiches.secondarykeyword", 
        "fields": {
            "word": "Avenches", 
            "parent": 181
        }
    }, 
    {
        "pk": 161, 
        "model": "fiches.secondarykeyword", 
        "fields": {
            "word": "B\u00e2le", 
            "parent": 181
        }
    }, 
    {
        "pk": 39, 
        "model": "fiches.secondarykeyword", 
        "fields": {
            "word": "Berne", 
            "parent": 181
        }
    }, 
    {
        "pk": 103, 
        "model": "fiches.secondarykeyword", 
        "fields": {
            "word": "Danemark", 
            "parent": 181
        }
    }, 
    {
        "pk": 69, 
        "model": "fiches.secondarykeyword", 
        "fields": {
            "word": "Ecosse", 
            "parent": 181
        }
    }, 
    {
        "pk": 131, 
        "model": "fiches.secondarykeyword", 
        "fields": {
            "word": "Espagne", 
            "parent": 181
        }
    }, 
    {
        "pk": 125, 
        "model": "fiches.secondarykeyword", 
        "fields": {
            "word": "Europe", 
            "parent": 181
        }
    }, 
    {
        "pk": 46, 
        "model": "fiches.secondarykeyword", 
        "fields": {
            "word": "France", 
            "parent": 181
        }
    }, 
    {
        "pk": 88, 
        "model": "fiches.secondarykeyword", 
        "fields": {
            "word": "Gen\u00e8ve", 
            "parent": 181
        }
    }, 
    {
        "pk": 134, 
        "model": "fiches.secondarykeyword", 
        "fields": {
            "word": "Gr\u00e8ce", 
            "parent": 181
        }
    }, 
    {
        "pk": 70, 
        "model": "fiches.secondarykeyword", 
        "fields": {
            "word": "Italie", 
            "parent": 181
        }
    }, 
    {
        "pk": 64, 
        "model": "fiches.secondarykeyword", 
        "fields": {
            "word": "Lausanne", 
            "parent": 181
        }
    }, 
    {
        "pk": 63, 
        "model": "fiches.secondarykeyword", 
        "fields": {
            "word": "Morges", 
            "parent": 181
        }
    }, 
    {
        "pk": 170, 
        "model": "fiches.secondarykeyword", 
        "fields": {
            "word": "Neuch\u00e2tel", 
            "parent": 181
        }
    }, 
    {
        "pk": 58, 
        "model": "fiches.secondarykeyword", 
        "fields": {
            "word": "Nyon", 
            "parent": 181
        }
    }, 
    {
        "pk": 60, 
        "model": "fiches.secondarykeyword", 
        "fields": {
            "word": "Orbe", 
            "parent": 181
        }
    }, 
    {
        "pk": 111, 
        "model": "fiches.secondarykeyword", 
        "fields": {
            "word": "Pays de Vaud", 
            "parent": 181
        }
    }, 
    {
        "pk": 108, 
        "model": "fiches.secondarykeyword", 
        "fields": {
            "word": "Pays-Bas", 
            "parent": 181
        }
    }, 
    {
        "pk": 132, 
        "model": "fiches.secondarykeyword", 
        "fields": {
            "word": "Portugal", 
            "parent": 181
        }
    }, 
    {
        "pk": 59, 
        "model": "fiches.secondarykeyword", 
        "fields": {
            "word": "Rolle", 
            "parent": 181
        }
    }, 
    {
        "pk": 150, 
        "model": "fiches.secondarykeyword", 
        "fields": {
            "word": "Rome", 
            "parent": 181
        }
    }, 
    {
        "pk": 87, 
        "model": "fiches.secondarykeyword", 
        "fields": {
            "word": "Russie", 
            "parent": 181
        }
    }, 
    {
        "pk": 162, 
        "model": "fiches.secondarykeyword", 
        "fields": {
            "word": "Soleure", 
            "parent": 181
        }
    }, 
    {
        "pk": 163, 
        "model": "fiches.secondarykeyword", 
        "fields": {
            "word": "Suisse", 
            "parent": 181
        }
    }, 
    {
        "pk": 62, 
        "model": "fiches.secondarykeyword", 
        "fields": {
            "word": "Vevey", 
            "parent": 181
        }
    }, 
    {
        "pk": 61, 
        "model": "fiches.secondarykeyword", 
        "fields": {
            "word": "Yverdon", 
            "parent": 181
        }
    }, 
    {
        "pk": 185, 
        "model": "fiches.secondarykeyword", 
        "fields": {
            "word": "Zurich", 
            "parent": 181
        }
    }, 
    {
        "pk": 75, 
        "model": "fiches.secondarykeyword", 
        "fields": {
            "word": "Bienfaisance", 
            "parent": 7
        }
    }, 
    {
        "pk": 183, 
        "model": "fiches.secondarykeyword", 
        "fields": {
            "word": "Bonheur", 
            "parent": 7
        }
    }, 
    {
        "pk": 74, 
        "model": "fiches.secondarykeyword", 
        "fields": {
            "word": "Charit\u00e9", 
            "parent": 7
        }
    }, 
    {
        "pk": 112, 
        "model": "fiches.secondarykeyword", 
        "fields": {
            "word": "Citoyen", 
            "parent": 7
        }
    }, 
    {
        "pk": 164, 
        "model": "fiches.secondarykeyword", 
        "fields": {
            "word": "Cosmopolitisme", 
            "parent": 7
        }
    }, 
    {
        "pk": 43, 
        "model": "fiches.secondarykeyword", 
        "fields": {
            "word": "Emulation", 
            "parent": 7
        }
    }, 
    {
        "pk": 198, 
        "model": "fiches.secondarykeyword", 
        "fields": {
            "word": "Epicurisme", 
            "parent": 7
        }
    }, 
    {
        "pk": 109, 
        "model": "fiches.secondarykeyword", 
        "fields": {
            "word": "Ethique", 
            "parent": 7
        }
    }, 
    {
        "pk": 186, 
        "model": "fiches.secondarykeyword", 
        "fields": {
            "word": "Imagination", 
            "parent": 7
        }
    }, 
    {
        "pk": 143, 
        "model": "fiches.secondarykeyword", 
        "fields": {
            "word": "Lumi\u00e8res", 
            "parent": 7
        }
    }, 
    {
        "pk": 202, 
        "model": "fiches.secondarykeyword", 
        "fields": {
            "word": "Raison", 
            "parent": 7
        }
    }, 
    {
        "pk": 146, 
        "model": "fiches.secondarykeyword", 
        "fields": {
            "word": "Scepticisme", 
            "parent": 7
        }
    }, 
    {
        "pk": 153, 
        "model": "fiches.secondarykeyword", 
        "fields": {
            "word": "Sentiments", 
            "parent": 7
        }
    }, 
    {
        "pk": 160, 
        "model": "fiches.secondarykeyword", 
        "fields": {
            "word": "Th\u00e9odic\u00e9e", 
            "parent": 7
        }
    }, 
    {
        "pk": 158, 
        "model": "fiches.secondarykeyword", 
        "fields": {
            "word": "Tol\u00e9rance", 
            "parent": 7
        }
    }, 
    {
        "pk": 173, 
        "model": "fiches.secondarykeyword", 
        "fields": {
            "word": "Vertu", 
            "parent": 7
        }
    }, 
    {
        "pk": 129, 
        "model": "fiches.secondarykeyword", 
        "fields": {
            "word": "Administration", 
            "parent": 14
        }
    }, 
    {
        "pk": 48, 
        "model": "fiches.secondarykeyword", 
        "fields": {
            "word": "Aristocratie", 
            "parent": 14
        }
    }, 
    {
        "pk": 102, 
        "model": "fiches.secondarykeyword", 
        "fields": {
            "word": "Arm\u00e9e", 
            "parent": 14
        }
    }, 
    {
        "pk": 101, 
        "model": "fiches.secondarykeyword", 
        "fields": {
            "word": "Autorit\u00e9", 
            "parent": 14
        }
    }, 
    {
        "pk": 93, 
        "model": "fiches.secondarykeyword", 
        "fields": {
            "word": "Bourgeoisie", 
            "parent": 14
        }
    }, 
    {
        "pk": 144, 
        "model": "fiches.secondarykeyword", 
        "fields": {
            "word": "Censure", 
            "parent": 14
        }
    }, 
    {
        "pk": 114, 
        "model": "fiches.secondarykeyword", 
        "fields": {
            "word": "Communes", 
            "parent": 14
        }
    }, 
    {
        "pk": 104, 
        "model": "fiches.secondarykeyword", 
        "fields": {
            "word": "Conf\u00e9d\u00e9ration", 
            "parent": 14
        }
    }, 
    {
        "pk": 65, 
        "model": "fiches.secondarykeyword", 
        "fields": {
            "word": "Conservatisme", 
            "parent": 14
        }
    }, 
    {
        "pk": 76, 
        "model": "fiches.secondarykeyword", 
        "fields": {
            "word": "Consistoire", 
            "parent": 14
        }
    }, 
    {
        "pk": 135, 
        "model": "fiches.secondarykeyword", 
        "fields": {
            "word": "Constitution", 
            "parent": 14
        }
    }, 
    {
        "pk": 49, 
        "model": "fiches.secondarykeyword", 
        "fields": {
            "word": "D\u00e9mocratie", 
            "parent": 14
        }
    }, 
    {
        "pk": 177, 
        "model": "fiches.secondarykeyword", 
        "fields": {
            "word": "Despotisme", 
            "parent": 14
        }
    }, 
    {
        "pk": 171, 
        "model": "fiches.secondarykeyword", 
        "fields": {
            "word": "Egalit\u00e9", 
            "parent": 14
        }
    }, 
    {
        "pk": 191, 
        "model": "fiches.secondarykeyword", 
        "fields": {
            "word": "Etat", 
            "parent": 14
        }
    }, 
    {
        "pk": 167, 
        "model": "fiches.secondarykeyword", 
        "fields": {
            "word": "Exil", 
            "parent": 14
        }
    }, 
    {
        "pk": 100, 
        "model": "fiches.secondarykeyword", 
        "fields": {
            "word": "Gouvernement", 
            "parent": 14
        }
    }, 
    {
        "pk": 21, 
        "model": "fiches.secondarykeyword", 
        "fields": {
            "word": "Guerre/Paix", 
            "parent": 14
        }
    }, 
    {
        "pk": 142, 
        "model": "fiches.secondarykeyword", 
        "fields": {
            "word": "Immigration", 
            "parent": 14
        }
    }, 
    {
        "pk": 71, 
        "model": "fiches.secondarykeyword", 
        "fields": {
            "word": "Imp\u00f4ts", 
            "parent": 14
        }
    }, 
    {
        "pk": 118, 
        "model": "fiches.secondarykeyword", 
        "fields": {
            "word": "In\u00e9galit\u00e9", 
            "parent": 14
        }
    }, 
    {
        "pk": 57, 
        "model": "fiches.secondarykeyword", 
        "fields": {
            "word": "Liberalisme", 
            "parent": 14
        }
    }, 
    {
        "pk": 99, 
        "model": "fiches.secondarykeyword", 
        "fields": {
            "word": "Libert\u00e9", 
            "parent": 14
        }
    }, 
    {
        "pk": 37, 
        "model": "fiches.secondarykeyword", 
        "fields": {
            "word": "Mercenariat", 
            "parent": 14
        }
    }, 
    {
        "pk": 124, 
        "model": "fiches.secondarykeyword", 
        "fields": {
            "word": "Milice", 
            "parent": 14
        }
    }, 
    {
        "pk": 47, 
        "model": "fiches.secondarykeyword", 
        "fields": {
            "word": "Monarchie", 
            "parent": 14
        }
    }, 
    {
        "pk": 35, 
        "model": "fiches.secondarykeyword", 
        "fields": {
            "word": "Naturalisation", 
            "parent": 14
        }
    }, 
    {
        "pk": 50, 
        "model": "fiches.secondarykeyword", 
        "fields": {
            "word": "Noblesse", 
            "parent": 14
        }
    }, 
    {
        "pk": 67, 
        "model": "fiches.secondarykeyword", 
        "fields": {
            "word": "Opinion publique", 
            "parent": 14
        }
    }, 
    {
        "pk": 205, 
        "model": "fiches.secondarykeyword", 
        "fields": {
            "word": "Patriciat", 
            "parent": 14
        }
    }, 
    {
        "pk": 72, 
        "model": "fiches.secondarykeyword", 
        "fields": {
            "word": "Patriotisme", 
            "parent": 14
        }
    }, 
    {
        "pk": 36, 
        "model": "fiches.secondarykeyword", 
        "fields": {
            "word": "Politique europ\u00e9enne", 
            "parent": 14
        }
    }, 
    {
        "pk": 33, 
        "model": "fiches.secondarykeyword", 
        "fields": {
            "word": "Population", 
            "parent": 14
        }
    }, 
    {
        "pk": 168, 
        "model": "fiches.secondarykeyword", 
        "fields": {
            "word": "R\u00e9gicide", 
            "parent": 14
        }
    }, 
    {
        "pk": 113, 
        "model": "fiches.secondarykeyword", 
        "fields": {
            "word": "R\u00e9publique", 
            "parent": 14
        }
    }, 
    {
        "pk": 40, 
        "model": "fiches.secondarykeyword", 
        "fields": {
            "word": "R\u00e9volte", 
            "parent": 14
        }
    }, 
    {
        "pk": 26, 
        "model": "fiches.secondarykeyword", 
        "fields": {
            "word": "R\u00e9volution", 
            "parent": 14
        }
    }, 
    {
        "pk": 204, 
        "model": "fiches.secondarykeyword", 
        "fields": {
            "word": "Science politique", 
            "parent": 14
        }
    }, 
    {
        "pk": 166, 
        "model": "fiches.secondarykeyword", 
        "fields": {
            "word": "Syst\u00e8me continental", 
            "parent": 14
        }
    }, 
    {
        "pk": 172, 
        "model": "fiches.secondarykeyword", 
        "fields": {
            "word": "Tyrannie", 
            "parent": 14
        }
    }, 
    {
        "pk": 184, 
        "model": "fiches.secondarykeyword", 
        "fields": {
            "word": "Utilit\u00e9 publique", 
            "parent": 14
        }
    }, 
    {
        "pk": 156, 
        "model": "fiches.secondarykeyword", 
        "fields": {
            "word": "Anabaptiste", 
            "parent": 18
        }
    }, 
    {
        "pk": 192, 
        "model": "fiches.secondarykeyword", 
        "fields": {
            "word": "Calvinisme", 
            "parent": 18
        }
    }, 
    {
        "pk": 221, 
        "model": "fiches.secondarykeyword", 
        "fields": {
            "word": "Cat\u00e9chisme", 
            "parent": 18
        }
    }, 
    {
        "pk": 127, 
        "model": "fiches.secondarykeyword", 
        "fields": {
            "word": "Catholicisme", 
            "parent": 18
        }
    }, 
    {
        "pk": 178, 
        "model": "fiches.secondarykeyword", 
        "fields": {
            "word": "Consensus", 
            "parent": 18
        }
    }, 
    {
        "pk": 159, 
        "model": "fiches.secondarykeyword", 
        "fields": {
            "word": "D\u00e9isme", 
            "parent": 18
        }
    }, 
    {
        "pk": 157, 
        "model": "fiches.secondarykeyword", 
        "fields": {
            "word": "Eglise", 
            "parent": 18
        }
    }, 
    {
        "pk": 179, 
        "model": "fiches.secondarykeyword", 
        "fields": {
            "word": "Papaut\u00e9", 
            "parent": 18
        }
    }, 
    {
        "pk": 105, 
        "model": "fiches.secondarykeyword", 
        "fields": {
            "word": "Pi\u00e9tisme", 
            "parent": 18
        }
    }, 
    {
        "pk": 126, 
        "model": "fiches.secondarykeyword", 
        "fields": {
            "word": "Protestantisme", 
            "parent": 18
        }
    }, 
    {
        "pk": 193, 
        "model": "fiches.secondarykeyword", 
        "fields": {
            "word": "Puritanisme", 
            "parent": 18
        }
    }, 
    {
        "pk": 201, 
        "model": "fiches.secondarykeyword", 
        "fields": {
            "word": "Astronomie", 
            "parent": 12
        }
    }, 
    {
        "pk": 20, 
        "model": "fiches.secondarykeyword", 
        "fields": {
            "word": "Corps", 
            "parent": 12
        }
    }, 
    {
        "pk": 187, 
        "model": "fiches.secondarykeyword", 
        "fields": {
            "word": "G\u00e9ologie", 
            "parent": 12
        }
    }, 
    {
        "pk": 188, 
        "model": "fiches.secondarykeyword", 
        "fields": {
            "word": "Math\u00e9matiques", 
            "parent": 12
        }
    }, 
    {
        "pk": 13, 
        "model": "fiches.secondarykeyword", 
        "fields": {
            "word": "M\u00e9decine", 
            "parent": 12
        }
    }, 
    {
        "pk": 189, 
        "model": "fiches.secondarykeyword", 
        "fields": {
            "word": "Physique", 
            "parent": 12
        }
    }, 
    {
        "pk": 78, 
        "model": "fiches.secondarykeyword", 
        "fields": {
            "word": "Acad\u00e9mie", 
            "parent": 19
        }
    }, 
    {
        "pk": 73, 
        "model": "fiches.secondarykeyword", 
        "fields": {
            "word": "Ecole de charit\u00e9", 
            "parent": 19
        }
    }, 
    {
        "pk": 8, 
        "model": "fiches.secondarykeyword", 
        "fields": {
            "word": "Education, enseignement", 
            "parent": 19
        }
    }, 
    {
        "pk": 190, 
        "model": "fiches.secondarykeyword", 
        "fields": {
            "word": "Famille", 
            "parent": 19
        }
    }, 
    {
        "pk": 147, 
        "model": "fiches.secondarykeyword", 
        "fields": {
            "word": "Femme", 
            "parent": 19
        }
    }, 
    {
        "pk": 145, 
        "model": "fiches.secondarykeyword", 
        "fields": {
            "word": "Franc-ma\u00e7onnerie", 
            "parent": 19
        }
    }, 
    {
        "pk": 195, 
        "model": "fiches.secondarykeyword", 
        "fields": {
            "word": "Grand tour", 
            "parent": 19
        }
    }, 
    {
        "pk": 42, 
        "model": "fiches.secondarykeyword", 
        "fields": {
            "word": "Groupe de Coppet", 
            "parent": 19
        }
    }, 
    {
        "pk": 22, 
        "model": "fiches.secondarykeyword", 
        "fields": {
            "word": "Jeu", 
            "parent": 19
        }
    }, 
    {
        "pk": 137, 
        "model": "fiches.secondarykeyword", 
        "fields": {
            "word": "M\u0153urs et morale", 
            "parent": 19
        }
    }, 
    {
        "pk": 90, 
        "model": "fiches.secondarykeyword", 
        "fields": {
            "word": "Pauvret\u00e9", 
            "parent": 19
        }
    }, 
    {
        "pk": 106, 
        "model": "fiches.secondarykeyword", 
        "fields": {
            "word": "Politesse", 
            "parent": 19
        }
    }, 
    {
        "pk": 169, 
        "model": "fiches.secondarykeyword", 
        "fields": {
            "word": "R\u00e9fugi\u00e9s", 
            "parent": 19
        }
    }, 
    {
        "pk": 94, 
        "model": "fiches.secondarykeyword", 
        "fields": {
            "word": "Soci\u00e9t\u00e9/Cercle/Assembl\u00e9e", 
            "parent": 19
        }
    }, 
    {
        "pk": 29, 
        "model": "fiches.secondarykeyword", 
        "fields": {
            "word": "Vie religieuse/croyances", 
            "parent": 19
        }
    }, 
    {
        "pk": 10, 
        "model": "fiches.secondarykeyword", 
        "fields": {
            "word": "Voyage", 
            "parent": 19
        }
    },
    {
        "pk": 1, 
        "model": "fiches.religion", 
        "fields": {
            "name": ""
        }
    }, 
    {
        "pk": 2, 
        "model": "fiches.religion", 
        "fields": {
            "name": "Protestant"
        }
    }, 
    {
        "pk": 3, 
        "model": "fiches.religion", 
        "fields": {
            "name": "Catholique"
        }
    }, 
    {
        "pk": 6, 
        "model": "fiches.religion", 
        "fields": {
            "name": "Juif"
        }
    }, 
    {
        "pk": 1, 
        "model": "fiches.documenttype", 
        "fields": {
            "code": 2, 
            "exclusive_fields": "", 
            "name": "Livre"
        }
    }, 
    {
        "pk": 2, 
        "model": "fiches.documenttype", 
        "fields": {
            "code": 1, 
            "exclusive_fields": "book_title", 
            "name": "Chapitre de livre"
        }
    }, 
    {
        "pk": 3, 
        "model": "fiches.documenttype", 
        "fields": {
            "code": 0, 
            "exclusive_fields": "journal_title, journal_num, journal_abr, series_title, series_text", 
            "name": "Article de revue"
        }
    }, 
    {
        "pk": 4, 
        "model": "fiches.documenttype", 
        "fields": {
            "code": -1, 
            "exclusive_fields": "dictionary_title", 
            "name": "Article de dictionnaire"
        }
    }, 
    {
        "pk": 2, 
        "model": "fiches.documentlanguage", 
        "fields": {
            "ordering": 1, 
            "code": "fr", 
            "name": "Fran\u00e7ais"
        }
    }, 
    {
        "pk": 3, 
        "model": "fiches.documentlanguage", 
        "fields": {
            "ordering": 2, 
            "code": "de", 
            "name": "Allemand"
        }
    }, 
    {
        "pk": 7, 
        "model": "fiches.documentlanguage", 
        "fields": {
            "ordering": 3, 
            "code": "it", 
            "name": "Italien"
        }
    }, 
    {
        "pk": 5, 
        "model": "fiches.documentlanguage", 
        "fields": {
            "ordering": 4, 
            "code": "en", 
            "name": "Anglais"
        }
    }, 
    {
        "pk": 6, 
        "model": "fiches.documentlanguage", 
        "fields": {
            "ordering": 5, 
            "code": "la", 
            "name": "Latin"
        }
    }, 
    {
        "pk": 1, 
        "model": "fiches.documentlanguage", 
        "fields": {
            "ordering": 6, 
            "code": "", 
            "name": ""
        }
    }, 
    {
        "pk": 1, 
        "model": "fiches.manuscripttype", 
        "fields": {
            "name": ""
        }
    }, 
    {
        "pk": 2, 
        "model": "fiches.manuscripttype", 
        "fields": {
            "name": "Lettre"
        }
    }, 
    {
        "pk": 4, 
        "model": "fiches.manuscripttype", 
        "fields": {
            "name": "Cahier"
        }
    }, 
    {
        "pk": 5, 
        "model": "fiches.manuscripttype", 
        "fields": {
            "name": ""
        }
    }, 
    {
        "pk": 7, 
        "model": "fiches.manuscripttype", 
        "fields": {
            "name": "Esquisse"
        }
    }, 
    {
        "pk": 8, 
        "model": "fiches.manuscripttype", 
        "fields": {
            "name": "Essai"
        }
    }, 
    {
        "pk": 9, 
        "model": "fiches.manuscripttype", 
        "fields": {
            "name": "Proc\u00e8s-verbaux"
        }
    }, 
    {
        "pk": 10, 
        "model": "fiches.manuscripttype", 
        "fields": {
            "name": "Correspondance"
        }
    }, 
    {
        "pk": 11, 
        "model": "fiches.manuscripttype", 
        "fields": {
            "name": "M\u00e9moires"
        }
    }, 
    {
        "pk": 12, 
        "model": "fiches.manuscripttype", 
        "fields": {
            "name": "Travail de s\u00e9minaire"
        }
    }, 
    {
        "pk": 13, 
        "model": "fiches.manuscripttype", 
        "fields": {
            "name": "Th\u00e8se de doctorat"
        }
    }, 
    {
        "pk": 1, 
        "model": "fiches.contributiontype", 
        "fields": {
            "code": 0, 
            "type": "any", 
            "name": "Auteur"
        }
    }, 
    {
        "pk": 2, 
        "model": "fiches.contributiontype", 
        "fields": {
            "code": 3, 
            "type": "any", 
            "name": "Collaborateur"
        }
    }, 
    {
        "pk": 3, 
        "model": "fiches.contributiontype", 
        "fields": {
            "code": 2, 
            "type": "any", 
            "name": "Traducteur"
        }
    }, 
    {
        "pk": 4, 
        "model": "fiches.contributiontype", 
        "fields": {
            "code": 2, 
            "type": "doc", 
            "name": "Editeur"
        }
    }, 
    {
        "pk": 5, 
        "model": "fiches.contributiontype", 
        "fields": {
            "code": 2, 
            "type": "doc", 
            "name": "Editeur de s\u00e9rie"
        }
    }, 
    {
        "pk": 6, 
        "model": "fiches.contributiontype", 
        "fields": {
            "code": -1, 
            "type": "man", 
            "name": "Destinataire"
        }
    }, 
    {
        "pk": 1, 
        "model": "fiches.relationtype", 
        "fields": {
            "sorting": 10, 
            "reverse_name": "Fille/Fils", 
            "name": "P\u00e8re"
        }
    }, 
    {
        "pk": 2, 
        "model": "fiches.relationtype", 
        "fields": {
            "sorting": 20, 
            "reverse_name": "Fille/Fils", 
            "name": "M\u00e8re"
        }
    }, 
    {
        "pk": 10, 
        "model": "fiches.relationtype", 
        "fields": {
            "sorting": 30, 
            "reverse_name": "Soeur/Fr\u00e8re", 
            "name": "Fr\u00e8re"
        }
    }, 
    {
        "pk": 11, 
        "model": "fiches.relationtype", 
        "fields": {
            "sorting": 40, 
            "reverse_name": "Soeur/Fr\u00e8re", 
            "name": "Soeur"
        }
    }, 
    {
        "pk": 12, 
        "model": "fiches.relationtype", 
        "fields": {
            "sorting": 50, 
            "reverse_name": "Conjoint", 
            "name": "Conjoint"
        }
    }, 
    {
        "pk": 3, 
        "model": "fiches.relationtype", 
        "fields": {
            "sorting": 60, 
            "reverse_name": "filleul-e", 
            "name": "Parrain"
        }
    }, 
    {
        "pk": 4, 
        "model": "fiches.relationtype", 
        "fields": {
            "sorting": 70, 
            "reverse_name": "filleul-e", 
            "name": "Marraine"
        }
    }, 
    {
        "pk": 13, 
        "model": "fiches.relationtype", 
        "fields": {
            "sorting": 80, 
            "reverse_name": "Autre lien de parent\u00e9", 
            "name": "Autre lien de parent\u00e9"
        }
    }, 
    {
        "pk": 6, 
        "model": "fiches.relationtype", 
        "fields": {
            "sorting": 100, 
            "reverse_name": "Connaissance", 
            "name": "Connaissance"
        }
    }, 
    {
        "pk": 8, 
        "model": "fiches.relationtype", 
        "fields": {
            "sorting": 110, 
            "reverse_name": "Contact \u00e9loign\u00e9", 
            "name": "Contact \u00e9loign\u00e9"
        }
    }, 
    {
        "pk": 5, 
        "model": "fiches.relationtype", 
        "fields": {
            "sorting": 120, 
            "reverse_name": "Correspondant", 
            "name": "Correspondant"
        }
    }, 
    {
        "pk": 9, 
        "model": "fiches.relationtype", 
        "fields": {
            "sorting": 130, 
            "reverse_name": "Est cit\u00e9 par", 
            "name": "Cite"
        }
    }, 
    {
        "pk": 7, 
        "model": "fiches.relationtype", 
        "fields": {
            "sorting": 145, 
            "reverse_name": "Traduit par", 
            "name": "Traducteur"
        }
    }, 
    {
        "pk": 1, 
        "model": "fiches.usergroup", 
        "fields": {
            "users": [], 
            "name": "Groupe Un", 
            "groups": [
                5
            ], 
            "description": ""
        }
    }, 
    {
        "pk": 2, 
        "model": "fiches.usergroup", 
        "fields": {
            "users": [
                1, 
                2, 
                6
            ], 
            "name": "Groupe deux", 
            "groups": [], 
            "description": ""
        }
    }
]
